mmtfPyspark/__init__.py
mmtfPyspark/structureViewer.py
mmtfPyspark/datasets/__init__.py
mmtfPyspark/datasets/advancedSearchDataset.py
mmtfPyspark/datasets/customReportService.py
mmtfPyspark/datasets/dataset_utils.py
mmtfPyspark/datasets/dbPtmDataset.py
mmtfPyspark/datasets/dbSnpDataset.py
mmtfPyspark/datasets/drugBankDataset.py
mmtfPyspark/datasets/g2sDataset.py
mmtfPyspark/datasets/groupInteractionExtractor.py
mmtfPyspark/datasets/jpredDataset.py
mmtfPyspark/datasets/myVariantDataset.py
mmtfPyspark/datasets/pdbPtmDataset.py
mmtfPyspark/datasets/pdbToUniProt.py
mmtfPyspark/datasets/pdbjMineDataset.py
mmtfPyspark/datasets/polymerSequenceExtractor.py
mmtfPyspark/datasets/secondaryStructureElementExtractor.py
mmtfPyspark/datasets/secondaryStructureExtractor.py
mmtfPyspark/datasets/secondaryStructureSegmentExtractor.py
mmtfPyspark/datasets/swissModelDataset.py
mmtfPyspark/datasets/uniProt.py
mmtfPyspark/filters/__init__.py
mmtfPyspark/filters/containsAlternativeLocations.py
mmtfPyspark/filters/containsDProteinChain.py
mmtfPyspark/filters/containsDSaccharideChain.py
mmtfPyspark/filters/containsDnaChain.py
mmtfPyspark/filters/containsGroup.py
mmtfPyspark/filters/containsLProteinChain.py
mmtfPyspark/filters/containsPolymerChainType.py
mmtfPyspark/filters/containsRnaChain.py
mmtfPyspark/filters/containsSequenceRegex.py
mmtfPyspark/filters/depositionDate.py
mmtfPyspark/filters/experimentalMethods.py
mmtfPyspark/filters/notFilter.py
mmtfPyspark/filters/orFilter.py
mmtfPyspark/filters/polymerComposition.py
mmtfPyspark/filters/rFree.py
mmtfPyspark/filters/rWork.py
mmtfPyspark/filters/releaseDate.py
mmtfPyspark/filters/resolution.py
mmtfPyspark/filters/secondaryStructure.py
mmtfPyspark/interactions/ExcludedLigandSets.py
mmtfPyspark/interactions/__init__.py
mmtfPyspark/interactions/atomInteraction.py
mmtfPyspark/interactions/coordinationGeometry.py
mmtfPyspark/interactions/groupInteractionExtractor.py
mmtfPyspark/interactions/interactionCenter.py
mmtfPyspark-0.3.6.dist-info/LICENSE.txt
mmtfPyspark-0.3.6.dist-info/METADATA
mmtfPyspark-0.3.6.dist-info/WHEEL
mmtfPyspark-0.3.6.dist-info/top_level.txt
mmtfPyspark-0.3.6.dist-info/RECORD
