Metadata-Version: 2.1
Name: mmtfPyspark
Version: 0.3.6
Summary: Methods for parallel and distributed analysis and mining of the Protein Data Bank using MMTF and Apache Spark
Home-page: https://github.com/sbl-sdsc/mmtf-pyspark
Author: Peter Rose
Author-email: pwrose.ucsd@gmail.com
License: Apache License 2.0
Keywords: mmtf spark pyspark protein PDB
Platform: UNKNOWN
Classifier: Development Status :: 3 - Alpha
Classifier: Intended Audience :: Science/Research
Classifier: Topic :: Scientific/Engineering :: Bio-Informatics
Classifier: License :: OSI Approved :: Apache Software License
Classifier: Programming Language :: Python :: 3.6
Requires-Python: >=3.6
Requires-Dist: msgpack (==0.5.6)
Requires-Dist: numpy (==1.15.4)
Requires-Dist: ipywidgets (==7.4.2)
Requires-Dist: mmtf-python (==1.1.2)
Requires-Dist: requests (==2.20.0)
Requires-Dist: matplotlib (==2.2.3)
Requires-Dist: seaborn (==0.8.1)
Requires-Dist: sympy (==1.1.1)
Requires-Dist: py3Dmol (==0.8.0)
Requires-Dist: scipy (==1.1.0)
Requires-Dist: scikit-learn (==0.20.0)
Requires-Dist: pandas (==0.23.4)
Requires-Dist: py4j (==0.10.7)
Requires-Dist: pyarrow (==0.11.1)
Requires-Dist: xlrd (==1.1.0)
